micro_test/__init__.py
micro_test/exceptions.py
micro_test/main.py
micro_test/micro_test.py
micro_test/tests.py
micro_test/utils.py
testify/__init__.py
testify/exceptions.py
testify/main.py
testify/tests.py
testify/utils.py
micro_test-0.0.2.dist-info/LICENSE
micro_test-0.0.2.dist-info/METADATA
micro_test-0.0.2.dist-info/WHEEL
micro_test-0.0.2.dist-info/top_level.txt
micro_test-0.0.2.dist-info/RECORD
