Metadata-Version: 2.1
Name: micro_test
Version: 0.0.2
Summary: Micro-framework de testes unitários minimalista
Home-page: https://github.com/andreluizmb82/micro_test.git
Author: Andre Luiz
Author-email: andreluizmb28@gmail.com
Classifier: Programming Language :: Python :: 3
Classifier: License :: OSI Approved :: MIT License
Classifier: Operating System :: OS Independent
Requires-Python: >=3.12
License-File: LICENSE
